deglib_cpp.cpython-310-darwin.so
deglib-0.1.6.dist-info/RECORD
deglib-0.1.6.dist-info/WHEEL
deglib-0.1.6.dist-info/top_level.txt
deglib-0.1.6.dist-info/METADATA
deglib-0.1.6.dist-info/licenses/LICENSE
deglib/analysis.py
deglib/distances.py
deglib/graph.py
deglib/std.py
deglib/__init__.py
deglib/builder.py
deglib/utils.py
deglib/search.py
deglib/repository.py
