Metadata-Version: 2.4
Name: deglib
Version: 0.1.6
Summary: Python bindings for the Dynamic Exploration Graph library by Nico Hezel
Author: Nico Hezel
Author-email: Bruno Schilling <bruno.schilling@htw-berlin.de>
Project-URL: Homepage, https://github.com/Visual-Computing/DynamicExplorationGraph
Keywords: anns-search,graph,python
Classifier: Development Status :: 2 - Pre-Alpha
Classifier: Intended Audience :: Developers
Classifier: Programming Language :: Python :: 3
Requires-Python: >=3.10
License-File: LICENSE
Requires-Dist: numpy>=2.2
Requires-Dist: psutil
Provides-Extra: test
Requires-Dist: pytest>=8.0; extra == "test"
Dynamic: license-file
